README.rst
setup.py
django_webtopay.egg-info/PKG-INFO
django_webtopay.egg-info/SOURCES.txt
django_webtopay.egg-info/dependency_links.txt
django_webtopay.egg-info/requires.txt
django_webtopay.egg-info/top_level.txt
webtopay/__init__.py
webtopay/admin.py
webtopay/cert.py
webtopay/conf.py
webtopay/forms.py
webtopay/models.py
webtopay/signals.py
webtopay/tests.py
webtopay/views.py
webtopay/widgets.py
webtopay/migrations/0001_initial.py
webtopay/migrations/0002_auto__del_field_webtopayresponse_status.py
webtopay/migrations/0003_auto__add_field_webtopayresponse_status.py
webtopay/migrations/__init__.py
webtopay/urls/__init__.py
webtopay/urls/makro.py
webtopay/urls/mikro.py