Metadata-Version: 1.1
Name: django-webtopay
Version: 1.0.1
Summary: A pluggable Django application for integrating WebToPay Payments
Home-page: https://github.com/Motiejus/django-webtopay
Author: Motiejus Jakštys
Author-email: desired.mta@gmail.com
License: UNKNOWN
Platform: UNKNOWN
Classifier: Framework :: Django
Classifier: Intended Audience :: Developers
Classifier: Programming Language :: Python :: 2.5
Classifier: Programming Language :: Python :: 2.6
Classifier: Programming Language :: Python :: 2.7
Classifier: Operating System :: OS Independent
Classifier: Topic :: Software Development
Classifier: License :: OSI Approved :: MIT License
